{
	"readOnly": false,
	"cells": [
		{
			"cell_type": "html",
			"source": "<b style=\"color:blue\">HTML cell ...</b>",
			"args": ""
		},
		{
			"cell_type": "code",
			"source": "<hr>\r\n<b style=\"color:blue\">Code cell...</b>\r\n<hr>\r\n<b style=\"color:gray\">with preview</b>\r\n<hr>\r\n",
			"args": "{\"preview\":\"preview\",\"showCode\":true}",
			"cell_h": 127
		},
		{
			"cell_type": "markdown",
			"source": "<b style=\"color:blue\">Markdown cell ...</b>\n\n## Tables\n\n---\n\n| Option | Description |\n| ------ | ----------- |\n| data   | path to data files to supply the data that will be passed into templates. |\n| engine | engine to be used for processing templates. Handlebars is the default. |\n| ext    | extension to be used for dest files. |\n\n---\n"
		}
	]
}
